invenio_pidstore/__init__.py
invenio_pidstore/admin.py
invenio_pidstore/cli.py
invenio_pidstore/config.py
invenio_pidstore/errors.py
invenio_pidstore/ext.py
invenio_pidstore/fetchers.py
invenio_pidstore/minters.py
invenio_pidstore/models.py
invenio_pidstore/proxies.py
invenio_pidstore/resolver.py
invenio_pidstore/alembic/999c62899c20_create_pidstore_tables.py
invenio_pidstore/alembic/f615cee99600_create_pidstore_branch.py
invenio_pidstore/providers/__init__.py
invenio_pidstore/providers/base.py
invenio_pidstore/providers/datacite.py
invenio_pidstore/providers/recordid.py
invenio_pidstore/providers/recordid_v2.py
invenio_pidstore/translations/messages.pot
invenio_pidstore/translations/ar/LC_MESSAGES/messages.mo
invenio_pidstore/translations/ar/LC_MESSAGES/messages.po
invenio_pidstore/translations/bg/LC_MESSAGES/messages.mo
invenio_pidstore/translations/bg/LC_MESSAGES/messages.po
invenio_pidstore/translations/ca/LC_MESSAGES/messages.mo
invenio_pidstore/translations/ca/LC_MESSAGES/messages.po
invenio_pidstore/translations/cs/LC_MESSAGES/messages.mo
invenio_pidstore/translations/cs/LC_MESSAGES/messages.po
invenio_pidstore/translations/da/LC_MESSAGES/messages.mo
invenio_pidstore/translations/da/LC_MESSAGES/messages.po
invenio_pidstore/translations/de/LC_MESSAGES/messages.mo
invenio_pidstore/translations/de/LC_MESSAGES/messages.po
invenio_pidstore/translations/el/LC_MESSAGES/messages.mo
invenio_pidstore/translations/el/LC_MESSAGES/messages.po
invenio_pidstore/translations/es/LC_MESSAGES/messages.mo
invenio_pidstore/translations/es/LC_MESSAGES/messages.po
invenio_pidstore/translations/et/LC_MESSAGES/messages.mo
invenio_pidstore/translations/et/LC_MESSAGES/messages.po
invenio_pidstore/translations/fa/LC_MESSAGES/messages.mo
invenio_pidstore/translations/fa/LC_MESSAGES/messages.po
invenio_pidstore/translations/fi/LC_MESSAGES/messages.mo
invenio_pidstore/translations/fi/LC_MESSAGES/messages.po
invenio_pidstore/translations/fr/LC_MESSAGES/messages.mo
invenio_pidstore-2.2.2.dist-info/licenses/AUTHORS.rst
invenio_pidstore-2.2.2.dist-info/licenses/LICENSE
invenio_pidstore-2.2.2.dist-info/METADATA
invenio_pidstore-2.2.2.dist-info/WHEEL
invenio_pidstore-2.2.2.dist-info/entry_points.txt
invenio_pidstore-2.2.2.dist-info/top_level.txt
invenio_pidstore-2.2.2.dist-info/RECORD
