Metadata-Version: 2.4
Name: invenio-pidstore
Version: 2.2.2
Summary: "Invenio module that stores and registers persistent identifiers."
Home-page: https://github.com/inveniosoftware/invenio-pidstore
Author: CERN
Author-email: info@inveniosoftware.org
License: MIT
Keywords: invenio identifier DOI
Platform: any
Classifier: Development Status :: 5 - Production/Stable
Requires-Python: >=3.7
License-File: LICENSE
License-File: AUTHORS.rst
Requires-Dist: base32-lib>=1.0.1
Requires-Dist: importlib_metadata>=4.4
Requires-Dist: importlib_resources>=5.0
Requires-Dist: invenio-base<3.0.0,>=2.3.0
Requires-Dist: invenio-i18n<4.0.0,>=3.0.0
Provides-Extra: tests
Requires-Dist: pytest-black-ng>=0.4.0; extra == "tests"
Requires-Dist: Flask-Menu<3.0.0,>=2.0.0; extra == "tests"
Requires-Dist: invenio-admin<2.0.0,>=1.2.0; extra == "tests"
Requires-Dist: invenio-access<5.0.0,>=4.0.0; extra == "tests"
Requires-Dist: invenio-accounts<7.0.0,>=6.0.0; extra == "tests"
Requires-Dist: mock>=3.0.0; extra == "tests"
Requires-Dist: pytest-invenio<4.0.0,>=3.0.0; extra == "tests"
Requires-Dist: SQLAlchemy-Continuum>=1.3.11; extra == "tests"
Requires-Dist: datacite>=0.1.0; extra == "tests"
Requires-Dist: Sphinx>=4.5.0; extra == "tests"
Requires-Dist: invenio-db[mysql,postgresql,versioning]<3.0.0,>=2.0.0; extra == "tests"
Dynamic: license-file
